django_saml2_auth/__init__.py
django_saml2_auth/errors.py
django_saml2_auth/exceptions.py
django_saml2_auth/saml.py
django_saml2_auth/urls.py
django_saml2_auth/user.py
django_saml2_auth/utils.py
django_saml2_auth/views.py
django_saml2_auth/templates/django_saml2_auth/denied.html
django_saml2_auth/templates/django_saml2_auth/error.html
django_saml2_auth/templates/django_saml2_auth/signout.html
django_saml2_auth/tests/__init__.py
django_saml2_auth/tests/settings.py
django_saml2_auth/tests/test_saml.py
django_saml2_auth/tests/test_user.py
django_saml2_auth/tests/test_utils.py
django_saml2_no_jwt-0.1.0.dist-info/AUTHORS.md
django_saml2_no_jwt-0.1.0.dist-info/LICENSE
django_saml2_no_jwt-0.1.0.dist-info/METADATA
django_saml2_no_jwt-0.1.0.dist-info/WHEEL
django_saml2_no_jwt-0.1.0.dist-info/top_level.txt
django_saml2_no_jwt-0.1.0.dist-info/RECORD
