Metadata-Version: 2.1
Name: django-saml2-no-jwt
Version: 0.1.0
Summary: Django SAML2 Authentication Made Easy.
Home-page: https://github.com/MPickfield/django-saml2-no-jwt
Author: Fang Li
Author-email: surivlee+djsaml2auth@gmail.com
Maintainer: Mike Pickfield
Maintainer-email: m.b.pickfield@gmail.com
License: Apache 2.0
Keywords: django,saml,saml2sso,authentication,okta,standard
Classifier: Development Status :: 5 - Production/Stable
Classifier: Intended Audience :: Developers
Classifier: Topic :: Software Development :: Libraries :: Python Modules
Classifier: License :: OSI Approved :: Apache Software License
Classifier: Framework :: Django :: 2.2
Classifier: Framework :: Django :: 3.2
Classifier: Framework :: Django :: 4.0
Classifier: Framework :: Django :: 4.1
Classifier: Programming Language :: Python :: 3
Classifier: Programming Language :: Python :: 3.7
Classifier: Programming Language :: Python :: 3.8
Classifier: Programming Language :: Python :: 3.9
Classifier: Programming Language :: Python :: 3.10
Classifier: Programming Language :: Python :: 3.11
License-File: LICENSE
License-File: AUTHORS.md
Requires-Dist: pysaml2 ==7.3.0
Requires-Dist: PyJWT ==1.7.1
Requires-Dist: dictor ==0.1.11
Requires-Dist: setuptools >=67.8.0
